apiflood/__init__.py
apiflood/apiflood.py
apiflood-0.1.dist-info/licenses/LICENSE
apiflood-0.1.dist-info/METADATA
apiflood-0.1.dist-info/WHEEL
apiflood-0.1.dist-info/top_level.txt
apiflood-0.1.dist-info/RECORD
