Metadata-Version: 2.4
Name: apiflood
Version: 0.1
Summary: DESTROY SOME APIS!!!
Author: Pankoza3-pl
Classifier: Programming Language :: Python :: 3
Classifier: License :: OSI Approved :: MIT License
License-File: LICENSE
Requires-Dist: requests
Dynamic: author
Dynamic: classifier
Dynamic: license-file
Dynamic: requires-dist
Dynamic: summary
